svsbench/__init__.py
svsbench/build.py
svsbench/compress.py
svsbench/consts.py
svsbench/generate_ground_truth.py
svsbench/loader.py
svsbench/merge.py
svsbench/search.py
svsbench/utils.py
svsbench-0.1.0.dist-info/METADATA
svsbench-0.1.0.dist-info/WHEEL
svsbench-0.1.0.dist-info/licenses/LICENSE
svsbench-0.1.0.dist-info/licenses/NOTICE
svsbench-0.1.0.dist-info/RECORD
