Metadata-Version: 2.4
Name: svsbench
Version: 0.1.0
Summary: Benchmarking for Scalable Vector Search
Author-email: Mihai Capotă <mihai.capota@intel.com>
License-File: LICENSE
License-File: NOTICE
Requires-Python: >=3.12
Requires-Dist: numpy>=1.10
Requires-Dist: scalable-vs>=0.0.7
Requires-Dist: tqdm>=4.67
